pyright/__init__.py
pyright/__main__.py
pyright/_mureq.py
pyright/_utils.py
pyright/_version.py
pyright/cli.py
pyright/errors.py
pyright/langserver.py
pyright/node.py
pyright/py.typed
pyright/types.py
pyright/utils.py
pyright-1.1.392.dist-info/LICENSE
pyright-1.1.392.dist-info/METADATA
pyright-1.1.392.dist-info/WHEEL
pyright-1.1.392.dist-info/entry_points.txt
pyright-1.1.392.dist-info/top_level.txt
pyright-1.1.392.dist-info/RECORD
