Metadata-Version: 2.1
Name: pyright
Version: 1.1.392
Summary: Command line wrapper for pyright
Home-page: https://github.com/RobertCraigie/pyright-python
Author: Robert Craigie
Maintainer: Robert Craigie
License: MIT
Project-URL: Source, https://github.com/RobertCraigie/pyright-python
Project-URL: Tracker, https://github.com/RobertCraigie/pyright-python/issues
Platform: UNKNOWN
Classifier: Development Status :: 5 - Production/Stable
Classifier: Intended Audience :: Developers
Classifier: Typing :: Typed
Classifier: Topic :: Software Development :: Libraries :: Python Modules
Classifier: Programming Language :: Python :: 3.7
Classifier: Programming Language :: Python :: 3.8
Classifier: Programming Language :: Python :: 3.9
Classifier: Programming Language :: Python :: 3.10
Classifier: Programming Language :: Python :: 3.11
Classifier: Programming Language :: Python :: 3.12
Requires-Python: >=3.7
License-File: LICENSE
Requires-Dist: nodeenv>=1.6.0
Requires-Dist: typing-extensions>=4.1
Provides-Extra: all
Requires-Dist: twine>=3.4.1; extra == "all"
Requires-Dist: nodejs-wheel-binaries; extra == "all"
Provides-Extra: dev
Requires-Dist: twine>=3.4.1; extra == "dev"
Provides-Extra: nodejs
Requires-Dist: nodejs-wheel-binaries; extra == "nodejs"
